pyrdt/__init__.py
pyrdt/atom.py
pyrdt/combo.py
pyrdt/math.py
pyrdt/stat.py
pywfz/__init__.py
pywfz/sql.py
pywfz/util.py
pywfz-1.0.1.dist-info/LICENSE
pywfz-1.0.1.dist-info/METADATA
pywfz-1.0.1.dist-info/WHEEL
pywfz-1.0.1.dist-info/top_level.txt
pywfz-1.0.1.dist-info/RECORD
