Metadata-Version: 2.1
Name: pywfz
Version: 1.0.1
Summary: reshape data type in py language 
Home-page: http://www.reshapedata.com
Author: hulilei
Author-email: hulilei@takewiki.com.cn
License: Apache License
Keywords: reshapedata,rdt,pyrdt
Platform: UNKNOWN
Requires-Python: >=3.6
Requires-Dist: requests
